{
  "conversation": [
    {
      "speaker": "Kabir",
      "text": "Arre welcome back folks! [laughs] Toh Ananya, kya scene hai with our Mumbai Indians, yaar?"
    },
    {
      "speaker": "Ananya",
      "text": "Kabir, sahi mein, woh log toh record tod team hai! 5 IPL titles, seriously? Pagalpan!"
    },
    {
      "speaker": "Kabir",
      "text": "Bilkul, Rohit Sharma and team ka asli dhamaka! But yeh bata, kya Jayawardene aur Pandya ki combo kaisi lagi?"
    },
    {
      "speaker": "Ananya",
      "text": "[sighs] Bhai, deadly duo! Kya strategy banti hai unki, next level! Ab dekhna kaun rokta unhe."
    },
    {
      "speaker": "Kabir",
      "text": "Haan, aur waha batting mein Pollard aur bowling mein Malinga, wah bhai! Kya mast mix hai!"
    },
    {
      "speaker": "Ananya",
      "text": "[laughs] Exactly! MI ka toh bas ek hi formula\u2014har season dhamaka! High-five for true blue MI fans!"
    }
  ]
}